csep/__init__.py
csep/models.py
csep/plots.py
csep/artifacts/runtime_config.tmpl
csep/artifacts/runtime_data.json
csep/artifacts/runtime_setup.yml
csep/artifacts/ExampleBasemaps/basemap_california.tif
csep/artifacts/ExampleForecasts/CatalogForecasts/ucerf3-landers_1992-06-28T11-57-34-14.csv
csep/artifacts/ExampleForecasts/GriddedForecasts/GEAR1_downsampled.dat
csep/artifacts/ExampleForecasts/GriddedForecasts/HiRes_SSM_Italy.dat
csep/artifacts/ExampleForecasts/GriddedForecasts/helmstetter_et_al.hkj-fromXML.dat
csep/artifacts/ExampleForecasts/GriddedForecasts/helmstetter_et_al.hkj.aftershock-fromXML.dat
csep/artifacts/ExampleResults/Poisson_l-test/ltest_model_0.json
csep/artifacts/ExampleResults/Poisson_l-test/ltest_model_1.json
csep/artifacts/ExampleResults/Poisson_l-test/ltest_model_2.json
csep/artifacts/ExampleResults/Poisson_l-test/ltest_model_3.json
csep/artifacts/ExampleResults/Poisson_l-test/ltest_model_4.json
csep/artifacts/ExampleResults/Poisson_l-test/ltest_model_5.json
csep/artifacts/ExampleResults/Poisson_l-test/ltest_model_6.json
csep/artifacts/ObservedCatalogs/sample_comcat_catalog.csv
csep/artifacts/Regions/RELMCollectionArea.dat
csep/artifacts/Regions/RELMTestArea.dat
csep/artifacts/Regions/california_qk_zoom=12.txt
csep/artifacts/Regions/csep-forecast-template-M5.xml
csep/artifacts/Regions/forecast.italy.M5.xml
csep/artifacts/Regions/italy.collection.nodes.dat
csep/artifacts/Regions/italy.testing.nodes.dat
csep/artifacts/Regions/nz.collection.nodes.dat
csep/artifacts/Regions/nz.testing.nodes.dat
csep/artifacts/Regions/Polygons/California/RELMCollectionPolygon.txt
csep/artifacts/Regions/Polygons/California/RELMTestingPolygon.txt
csep/artifacts/Regions/Polygons/Italy/ItalyCollectionPolygon.txt
csep/artifacts/Regions/Polygons/Italy/ItalyTestingPolygon.txt
csep/core/__init__.py
csep/core/binomial_evaluations.py
csep/core/brier_evaluations.py
csep/core/catalog_evaluations.py
csep/core/catalogs.py
csep/core/exceptions.py
csep/core/forecasts.py
pycsep-0.8.0.dist-info/licenses/LICENSE
pycsep-0.8.0.dist-info/METADATA
pycsep-0.8.0.dist-info/WHEEL
pycsep-0.8.0.dist-info/top_level.txt
pycsep-0.8.0.dist-info/RECORD
