Metadata-Version: 2.4
Name: pycsep
Version: 0.8.0
Summary: Python tools from the Collaboratory for the Study of Earthquake Predictability
Author-email: William Savran <wsavran@unr.edu>
License: Copyright (c) 2021, The University of Southern California
Project-URL: Homepage, https://github.com/SCECCode/pycsep
Requires-Python: >=3.9
License-File: LICENSE
Requires-Dist: numpy
Requires-Dist: scipy
Requires-Dist: pandas
Requires-Dist: matplotlib
Requires-Dist: cartopy
Requires-Dist: obspy
Requires-Dist: pyproj
Requires-Dist: python-dateutil
Requires-Dist: rasterio
Requires-Dist: mercantile
Requires-Dist: shapely
Provides-Extra: dev
Requires-Dist: pytest; extra == "dev"
Requires-Dist: vcrpy; extra == "dev"
Requires-Dist: pytest-cov; extra == "dev"
Requires-Dist: sphinx; extra == "dev"
Requires-Dist: sphinx-gallery; extra == "dev"
Requires-Dist: sphinx-rtd-theme; extra == "dev"
Requires-Dist: pillow; extra == "dev"
Requires-Dist: tox; extra == "dev"
Dynamic: license-file
